update_notipy.py
update_notipy-0.1.2.dist-info/DESCRIPTION.rst
update_notipy-0.1.2.dist-info/METADATA
update_notipy-0.1.2.dist-info/RECORD
update_notipy-0.1.2.dist-info/WHEEL
update_notipy-0.1.2.dist-info/metadata.json
update_notipy-0.1.2.dist-info/top_level.txt
