Metadata-Version: 2.0
Name: update-notipy
Version: 0.1.2
Summary: Update notifications for your python app
Home-page: https://github.com/acifani/update-notipy
Author: Alessandro Cifani
Author-email: alessandro.cifani@gmail.com
License: BSD
Platform: UNKNOWN
Classifier: Development Status :: 3 - Alpha
Classifier: Intended Audience :: Developers
Classifier: License :: OSI Approved :: BSD License
Classifier: Operating System :: OS Independent
Classifier: Topic :: Software Development :: Libraries :: Python Modules
Classifier: Programming Language :: Python
Requires-Dist: pkg-info
Requires-Dist: boxing (>=0.1.4)
Requires-Dist: semver
Requires-Dist: colored
